{
    "sourceFile": "README.md",
    "activeCommit": 0,
    "commits": [
        {
            "activePatchIndex": 0,
            "patches": [
                {
                    "date": 1640315056094,
                    "content": "Index: \n===================================================================\n--- \n+++ \n"
                }
            ],
            "date": 1640315056094,
            "name": "Commit-0",
            "content": "# Digital-Circuits-Experiment\r\n \r\n## 2021秋季南京大学数字逻辑与计算机组成实验\r\n\r\n## 相关代码仅作参考，严禁抄袭\r\n\r\n感谢cjg、hs在实验12中做出的卓越贡献:)"
        }
    ]
}